LICENSE.md
README.md
setup.py
bincrafters/__init__.py
bincrafters/autodetect.py
bincrafters/build_autodetect.py
bincrafters/build_paths.py
bincrafters/build_shared.py
bincrafters/check_compatibility.py
bincrafters/cli.py
bincrafters/generate_ci_jobs.py
bincrafters/prepare_env.py
bincrafters/prepare_env_azp_windows.ps1
bincrafters/requirements.txt
bincrafters/requirements_test.txt
bincrafters/utils.py
bincrafters_package_tools.egg-info/PKG-INFO
bincrafters_package_tools.egg-info/SOURCES.txt
bincrafters_package_tools.egg-info/dependency_links.txt
bincrafters_package_tools.egg-info/entry_points.txt
bincrafters_package_tools.egg-info/requires.txt
bincrafters_package_tools.egg-info/top_level.txt