Metadata-Version: 2.1
Name: bincrafters-package-tools
Version: 0.33.0
Summary: Bincrafters Packaging tools for build Conan projects
Home-page: https://github.com/bincrafters/bincrafters-package-tools
Author: Bincrafters
Author-email: bincrafters@gmail.com
License: MIT
Keywords: conan,C/C++,package,libraries,developer,manager,dependency,tool,c,c++,cpp
Platform: UNKNOWN
Classifier: Development Status :: 4 - Beta
Classifier: Intended Audience :: Developers
Classifier: Topic :: Software Development :: Build Tools
Classifier: License :: OSI Approved :: MIT License
Classifier: Programming Language :: Python :: 3
Provides-Extra: test
